postman_collection_exporter/__init__.py
postman_collection_exporter/cli.py
postman_collection_exporter/enums.py
postman_collection_exporter/exceptions.py
postman_collection_exporter/exporters.py
postman_collection_exporter/helpers.py
postman_collection_exporter/structures.py
postman_collection_exporter/dependencies/__init__.py
postman_collection_exporter/dependencies/utils.py
postman_collection_exporter/logging/__init__.py
postman_collection_exporter/logging/config.py
postman_collection_exporter/scheduling/__init__.py
postman_collection_exporter/scheduling/cli.py
postman_collection_exporter/scheduling/crontab_helpers.py
postman_collection_exporter/scheduling/utils.py
postman_collection_exporter-0.0.9.dist-info/METADATA
postman_collection_exporter-0.0.9.dist-info/WHEEL
postman_collection_exporter-0.0.9.dist-info/entry_points.txt
postman_collection_exporter-0.0.9.dist-info/licenses/LICENSE
postman_collection_exporter-0.0.9.dist-info/RECORD
