Metadata-Version: 2.4
Name: postman-collection-exporter
Version: 0.0.9
Summary: Export Postman collections via CLI.
Project-URL: Homepage, https://github.com/sergey-vernyk/PostmanCollectionExporter
Project-URL: Issues, https://github.com/sergey-vernyk/PostmanCollectionExporter/issues
Project-URL: Repository, https://github.com/sergey-vernyk/PostmanCollectionExporter.git
Author-email: Sergey Vernigora <volt.awp.dev@gmail.com>
Maintainer-email: Sergey Vernigora <volt.awp.dev@gmail.com>
License-Expression: MIT
License-File: LICENSE
Keywords: cli,crontab,export,json,postman
Classifier: Environment :: Console
Classifier: License :: OSI Approved :: MIT License
Classifier: Operating System :: OS Independent
Classifier: Programming Language :: Python :: 3.11
Classifier: Programming Language :: Python :: 3.12
Classifier: Programming Language :: Python :: 3.13
Classifier: Topic :: Software Development :: Libraries
Classifier: Topic :: Terminals
Classifier: Topic :: Utilities
Requires-Python: >=3.11
Requires-Dist: aiofiles
Requires-Dist: anyio
Requires-Dist: asyncclick
Requires-Dist: httpx
Provides-Extra: schedule
Requires-Dist: python-crontab; extra == 'schedule'
Provides-Extra: test
Requires-Dist: pytest; extra == 'test'
Requires-Dist: pytest-asyncio; extra == 'test'
Requires-Dist: trio; extra == 'test'
